shipyard_portable/__init__.py
shipyard_portable/cli/authtest.py
shipyard_portable/cli/trigger.py
shipyard_portable/portable.py
shipyard_portable-0.1.0.dist-info/METADATA
shipyard_portable-0.1.0.dist-info/WHEEL
shipyard_portable-0.1.0.dist-info/RECORD
